gimpml/__init__.py
gimpml/filters/__init__.py
gimpml/filters/fog.py
gimpml/filters/gaussian_blur.py
gimpml/plugins/__init__.py
gimpml/plugins/plugin_utils.py
gimpml/plugins/canny/__init__.py
gimpml/plugins/canny/canny.py
gimpml/plugins/coloring/__init__.py
gimpml/plugins/coloring/coloring.py
gimpml/plugins/colorpalette/__init__.py
gimpml/plugins/colorpalette/color_palette.png
gimpml/plugins/colorpalette/colorpalette.py
gimpml/plugins/deblur/__init__.py
gimpml/plugins/deblur/deblur.py
gimpml/plugins/dehaze/__init__.py
gimpml/plugins/dehaze/dehaze.py
gimpml/plugins/denoise/__init__.py
gimpml/plugins/denoise/denoise.py
gimpml/plugins/detectobjects/__init__.py
gimpml/plugins/detectobjects/detectobjects.py
gimpml/plugins/enlighten/__init__.py
gimpml/plugins/enlighten/enlighten.py
gimpml/plugins/faceparse/__init__.py
gimpml/plugins/faceparse/faceparse.py
gimpml/plugins/filterfolder/__init__.py
gimpml/plugins/filterfolder/filterfolder.py
gimpml/plugins/images/__init__.py
gimpml/plugins/images/error_icon.png
gimpml/plugins/images/plugin_logo.png
gimpml/plugins/inpainting/__init__.py
gimpml/plugins/inpainting/inpainting.py
gimpml/plugins/interpolation/__init__.py
gimpml/plugins/interpolation/interpolation.py
gimpml/plugins/kmeans/__init__.py
gimpml/plugins/kmeans/kmeans.py
gimpml/plugins/matting/__init__.py
gimpml/plugins/matting/matting.py
gimpml/plugins/monodepth/__init__.py
gimpml/plugins/monodepth/monodepth.py
gimpml/plugins/semseg/__init__.py
gimpml/plugins/semseg/semseg.py
gimpml/plugins/superresolution/__init__.py
gimpml/plugins/superresolution/superresolution.py
gimpml/tools/__init__.py
gimpml/tools/canny.py
gimpml/tools/coloring.py
gimpml/tools/complete_install.py
gimpml/tools/deblur.py
gimpml/tools/dehaze.py
gimpml/tools/denoise.py
gimpml/tools/detectobjects.py
gimpml/tools/enlighten.py
gimpml/tools/faceparse.py
gimpml/tools/inpainting.py
gimpml/tools/interpolation.py
gimpml/tools/kmeans.py
gimpml/tools/matting.py
gimpml/tools/model_info.csv
gimpml-0.0.8.dist-info/METADATA
gimpml-0.0.8.dist-info/WHEEL
gimpml-0.0.8.dist-info/top_level.txt
gimpml-0.0.8.dist-info/RECORD
