Metadata-Version: 2.1
Name: gimpml
Version: 0.0.8
Summary: A.I. for GIMP
Home-page: https://github.com/kritiksoman/GIMP-ML
Author: Kritik Soman
Author-email: kritiksoman@ieee.org
License: UNKNOWN
Keywords: sample,setuptools,development
Platform: UNKNOWN
Classifier: Development Status :: 3 - Alpha
Classifier: Intended Audience :: Developers
Classifier: Topic :: Software Development :: Build Tools
Classifier: Programming Language :: Python :: 3.8
Requires-Python: >=2.7
Requires-Dist: numpy
Requires-Dist: scipy
Requires-Dist: gdown
Requires-Dist: typing
Requires-Dist: requests
Requires-Dist: opencv-python (<=4.3)
Requires-Dist: pretrainedmodels
Requires-Dist: scikit-image
Requires-Dist: timm (==0.4.5)
Requires-Dist: future ; python_version <= "2.7"
Requires-Dist: enum ; python_version <= "2.7"
